drw/__init__.py
drw/core.py
drw-0.1.0.dist-info/licenses/LICENSE
drw-0.1.0.dist-info/METADATA
drw-0.1.0.dist-info/WHEEL
drw-0.1.0.dist-info/top_level.txt
drw-0.1.0.dist-info/RECORD
