Metadata-Version: 2.4
Name: drw
Version: 0.1.0
Summary: A Python library for context-aware operations using an LLM
Author-email: Your Name <your.email@example.com>
License-Expression: MIT
Project-URL: Homepage, https://github.com/yourusername/drw
Classifier: Programming Language :: Python :: 3
Classifier: Operating System :: OS Independent
Requires-Python: >=3.6
License-File: LICENSE
Requires-Dist: google-generativeai>=0.7.0
Dynamic: license-file
